pydantic_visible_fields/__init__.py
pydantic_visible_fields/core.py
pydantic_visible_fields/paginatedresponse.py
pydantic_visible_fields/py.typed
pydantic_visible_fields-0.2.6.dist-info/licenses/LICENSE
pydantic_visible_fields-0.2.6.dist-info/METADATA
pydantic_visible_fields-0.2.6.dist-info/WHEEL
pydantic_visible_fields-0.2.6.dist-info/top_level.txt
pydantic_visible_fields-0.2.6.dist-info/RECORD
