Metadata-Version: 2.4
Name: pydantic-visible-fields
Version: 0.2.6
Summary: Field-level visibility control for Pydantic models
Author-email: Martin Alge <martin@alge.se>
License: MIT License
Project-URL: Bug Tracker, https://github.com/Alge/pydantic-visible-fields/issues
Project-URL: Documentation, https://github.com/Alge/pydantic-visible-fields#readme
Project-URL: Source Code, https://github.com/Alge/pydantic-visible-fields
Classifier: License :: OSI Approved :: MIT License
Classifier: Programming Language :: Python :: 3
Classifier: Programming Language :: Python :: 3.8
Classifier: Programming Language :: Python :: 3.9
Classifier: Programming Language :: Python :: 3.10
Classifier: Programming Language :: Python :: 3.11
Classifier: Programming Language :: Python :: 3.12
Classifier: Programming Language :: Python :: 3.13
Requires-Python: >=3.8
License-File: LICENSE
Requires-Dist: pydantic>=2.0.0
Provides-Extra: dev
Requires-Dist: pytest>=6.0; extra == "dev"
Requires-Dist: black>=21.5b2; extra == "dev"
Requires-Dist: isort>=5.0.0; extra == "dev"
Requires-Dist: mypy>=0.812; extra == "dev"
Requires-Dist: flake8>=3.9.2; extra == "dev"
Provides-Extra: doc
Requires-Dist: mkdocs>=1.1.2; extra == "doc"
Requires-Dist: mkdocs-material>=7.1.5; extra == "doc"
Requires-Dist: mkdocstrings>=0.15.2; extra == "doc"
Dynamic: license-file
